spectrum_card/__init__.py
spectrum_card/spectrum_header/py_header/regs.py
spectrum_card/spectrum_header/py_header/spcerr.py
spectrum_card/spectrum_header/pyspcm.py
spectrum_card/spectrum_header/spcm_tools.py
spectrum_card-1.1.0.dist-info/LICENSE
spectrum_card-1.1.0.dist-info/METADATA
spectrum_card-1.1.0.dist-info/WHEEL
spectrum_card-1.1.0.dist-info/RECORD
