Metadata-Version: 2.1
Name: spectrum-card
Version: 1.1.0
Summary: Wrapper to be used with AWG cards from Spectrum Instruments.
License: BSD 3 Clause
Author: Alexander Tritt Monash
Author-email: alexander.tritt@monash.edu
Requires-Python: >=3.8,<4.0
Classifier: License :: Other/Proprietary License
Classifier: Programming Language :: Python :: 3
Classifier: Programming Language :: Python :: 3.8
Classifier: Programming Language :: Python :: 3.9
Classifier: Programming Language :: Python :: 3.10
Classifier: Programming Language :: Python :: 3.11
